get_set_nested_dict/__init__.py
get_set_nested_dict-0.1.1.dist-info/LICENSE
get_set_nested_dict-0.1.1.dist-info/METADATA
get_set_nested_dict-0.1.1.dist-info/WHEEL
get_set_nested_dict-0.1.1.dist-info/top_level.txt
get_set_nested_dict-0.1.1.dist-info/RECORD
