Metadata-Version: 2.1
Name: get-set-nested-dict
Version: 0.1.1
Summary: Get or Set a nested value of nested dict by path
Home-page: https://github.com/Yellorn/get_set_nested_dict
Author: Hoang Yell
Author-email: ngohoang.yell@gmail.com
License: UNKNOWN
Platform: UNKNOWN
Classifier: Programming Language :: Python :: 3
Classifier: License :: OSI Approved :: MIT License
Classifier: Operating System :: OS Independent
Requires-Python: >=3.0
